guispec/__init__.py
guispec/guispec.py
guispec-0.0.1.dist-info/METADATA
guispec-0.0.1.dist-info/WHEEL
guispec-0.0.1.dist-info/top_level.txt
guispec-0.0.1.dist-info/RECORD
